Workbook

Sheet Painel de Controle
A1: 📊 SIMULADOR DE INVESTIMENTOS EM FIIs
A2: Atualizado em: 07/01/2026 14:01
A4: INDICADORES PRINCIPAIS
A5: Métrica | B5: Valor | D5: DISTRIBUIÇÃO POR SETOR
A6: Valor Total Investido | B6: =Carteira!K2 -> 134491.5 | D6: Setor | E6: Valor Investido | F6: %
A7: Valor Atual da Carteira | B7: =Carteira!L2 -> 139828 | D7: Residencial | E7: 42000 | F7: 0.28
A8: Rentabilidade Total (%) | B8: =(Carteira!L2-Carteira!K2)/Carteira!K2 -> 0.039679088 | D8: Comercial | E8: 48000 | F8: 0.32
A9: Dividend Yield Médio | B9: =MÉDIA(Carteira!I5:I16) -> #NAME? | D9: Industrial | E9: 37500 | F9: 0.25
A10: Rendimento Mensal Médio | B10: =Rendimentos!G14 | D10: Híbrido | E10: 22500 | F10: 0.15
A11: Total Rendimentos Recebidos | B11: =Rendimentos!G13

Sheet Carteira
A1: 💼 CARTEIRA DE FIIs
A2: TOTAIS: | K2: =SUM(G4:G15) -> 134491.5 | L2: =SUM(H4:H15) -> 139828
A3: Código | B3: Nome do FII | C3: Setor | D3: Cotas | E3: Preço Médio | F3: Preço Atual | G3: Valor Investido | H3: Valor Atual | I3: Dividend Yield | J3: Rend. Mensal | K3: TOTAL INVESTIDO | L3: TOTAL ATUAL
A4: HGLG11 | B4: CSHG Logística | C4: Industrial | D4: 120 | E4: 158.5 | F4: 165.2 | G4: =D4*E4 -> 19020 | H4: =D4*F4 -> 19824 | I4: 0.1125 | J4: =H4*I4 -> 2230.2
A5: CSHG11 | B5: CSHG Real Estate | C5: Comercial | D5: 95 | E5: 105.3 | F5: 112.8 | G5: =D5*E5 -> 10003.5 | H5: =D5*F5 -> 10716 | I5: 0.0985 | J5: =H5*I5 -> 1055.526
A6: BTLG11 | B6: BTG Logística | C6: Industrial | D6: 110 | E6: 98.2 | F6: 102.5 | G6: =D6*E6 -> 10802 | H6: =D6*F6 -> 11275 | I6: 0.105 | J6: =H6*I6 -> 1183.875
A7: XPLG11 | B7: XP Log | C7: Industrial | D7: 85 | E7: 105.8 | F7: 108.9 | G7: =D7*E7 -> 8993 | H7: =D7*F7 -> 9256.5 | I7: 0.092 | J7: =H7*I7 -> 851.598
A8: HGRU11 | B8: CSHG Renda Urbana | C8: Comercial | D8: 130 | E8: 115.4 | F8: 118.5 | G8: =D8*E8 -> 15002 | H8: =D8*F8 -> 15405 | I8: 0.1075 | J8: =H8*I8 -> 1656.0375
A9: KNCR11 | B9: Kinea Renda Imob. | C9: Híbrido | D9: 75 | E9: 95.6 | F9: 99.2 | G9: =D9*E9 -> 7170 | H9: =D9*F9 -> 7440 | I9: 0.088 | J9: =H9*I9 -> 654.72
A10: MXRF11 | B10: Maxi Renda | C10: Comercial | D10: 100 | E10: 105.9 | F10: 110.3 | G10: =D10*E10 -> 10590 | H10: =D10*F10 -> 11030 | I10: 0.1125 | J10: =H10*I10 -> 1240.875
A11: VISC11 | B11: Vinci Shopping | C11: Comercial | D11: 90 | E11: 98.7 | F11: 101.2 | G11: =D11*E11 -> 8883 | H11: =D11*F11 -> 9108 | I11: 0.095 | J11: =H11*I11 -> 865.26
A12: RZTR11 | B12: Riza Terrax | C12: Residencial | D12: 140 | E12: 89.5 | F12: 92.8 | G12: =D12*E12 -> 12530 | H12: =D12*F12 -> 12992 | I12: 0.1187 | J12: =H12*I12 -> 1542.1504
A13: PVBI11 | B13: VBI Prime | C13: Residencial | D13: 105 | E13: 98.3 | F13: 102.4 | G13: =D13*E13 -> 10321.5 | H13: =D13*F13 -> 10752 | I13: 0.105 | J13: =H13*I13 -> 1128.96
A14: RBVA11 | B14: RBR Alpha | C14: Híbrido | D14: 125 | E14: 88.9 | F14: 91.5 | G14: =D14*E14 -> 11112.5 | H14: =D14*F14 -> 11437.5 | I14: 0.0975 | J14: =H14*I14 -> 1115.1562
A15: XPML11 | B15: XP Malls | C15: Comercial | D15: 80 | E15: 125.8 | F15: 132.4 | G15: =D15*E15 -> 10064 | H15: =D15*F15 -> 10592 | I15: 0.102 | J15: =H15*I15 -> 1080.384

Sheet Rendimentos
A1: 💰 HISTÓRICO DE RENDIMENTOS
A3: Mês/Ano | B3: HGLG11 | C3: CSHG11 | D3: BTLG11 | E3: XPLG11 | F3: HGRU11 | G3: TOTAL
A4: Jan/2025 | B4: 185.5 | C4: 165.3 | D4: 142.8 | E4: 128.9 | F4: 195.4 | G4: =SUM(B4:F4) -> 817.9
A5: Fev/2025 | B5: 187.2 | C5: 168.5 | D5: 145.2 | E5: 131.2 | F5: 198.3 | G5: =SUM(B5:F5) -> 830.4
A6: Mar/2025 | B6: 189.8 | C6: 171.4 | D6: 148.1 | E6: 133.8 | F6: 201.5 | G6: =SUM(B6:F6) -> 844.6
A7: Abr/2025 | B7: 192.5 | C7: 174.2 | D7: 150.9 | E7: 136.4 | F7: 204.7 | G7: =SUM(B7:F7) -> 858.7
A8: Mai/2025 | B8: 195.3 | C8: 177.1 | D8: 153.8 | E8: 139.2 | F8: 208 | G8: =SUM(B8:F8) -> 873.4
A9: Jun/2025 | B9: 198.2 | C9: 180.2 | D9: 156.7 | E9: 142.1 | F9: 211.4 | G9: =SUM(B9:F9) -> 888.6
A10: Jul/2025 | B10: 201.1 | C10: 183.3 | D10: 159.8 | E10: 145 | F10: 214.9 | G10: =SUM(B10:F10) -> 904.1
A11: Ago/2025 | B11: 204.2 | C11: 186.5 | D11: 162.9 | E11: 148.1 | F11: 218.5 | G11: =SUM(B11:F11) -> 920.2
A12: Set/2025 | B12: 207.4 | C12: 189.8 | D12: 166.2 | E12: 151.3 | F12: 222.2 | G12: =SUM(B12:F12) -> 936.9
A13: Total: | B13: 210.7 | C13: 193.2 | D13: 169.5 | E13: 154.6 | F13: 226 | G13: =G16
A14: Média: | B14: 214.1 | C14: 196.7 | D14: 172.9 | E14: 158 | F14: 229.9 | G14: =G17
A15: Dez/2025 | B15: 217.6 | C15: 200.3 | D15: 176.5 | E15: 161.5 | F15: 233.9 | G15: =SUM(B15:F15) -> 989.8
A16: TOTAL ACUMULADO: | G16: =SUM(G4:G15)
A17: MÉDIA MENSAL: | G17: =AVERAGE(G4:G15)

Sheet Simulações
A1: 📈 SIMULADOR DE CENÁRIOS
A3: SIMULAR NOVO APORTE
A5: Valor do Aporte (R$): | B5: 5000
A6: Código do FII: | B6: HGLG11
A7: Preço Atual da Cota: | B7: 165.2
A9: RESULTADO:
A10: Quantidade de Cotas: | B10: =INT(B5/B7) -> 30
A11: Novo Total de Cotas: | B11: =Carteira!D4+B10 -> 150
A12: Rendimento Mensal Estimado: | B12: =(B11*B7)*Carteira!I4 -> 2787.75
A15: PROJEÇÃO DE RENTABILIDADE - 12 MESES
A16: Cenário | B16: Yield Anual | C16: Rendimento Mensal | D16: Total 12 Meses
A17: Conservador | B17: 0.09 | C17: =Carteira!L2*B17/12 -> 1048.71 | D17: =C17*12 -> 12584.52
A18: Moderado | B18: 0.11 | C18: =Carteira!L2*B18/12 -> 1281.7567 | D18: =C18*12 -> 15381.08
A19: Agressivo | B19: 0.14 | C19: =Carteira!L2*B19/12 -> 1631.3267 | D19: =C19*12 -> 19575.92
A22: SIMULAÇÃO DE REINVESTIMENTO
A24: Rendimento Mensal Médio: | B24: =Rendimentos!G14
A25: % para Reinvestir: | B25: 0.5
A26: Valor Reinvestido/Mês: | B26: =B24*B25
A27: Acumulado em 12 meses: | B27: =B26*12
A28: Acumulado em 24 meses: | B28: =B26*24

Sheet Dashboard
A1: 📉 DASHBOARD DE INDICADORES
A3: INDICADORES DE PERFORMANCE | E3: DISTRIBUIÇÃO MENSAL DE RENDIMENTOS
A4: Indicador | B4: Valor Atual | C4: Meta | D4: Status | E4: Mês | F4: Rendimento | G4: Var. %
A5: Patrimônio Total | B5: =Carteira!L2 -> 139828 | C5: 200000 | D5: =IF(B5>=C5,"✓ Atingido","⚠ Abaixo") -> ⚠ Abaixo | E5: Jan | F5: =Rendimentos!G4 -> 817.9 | G5: -
A6: Rendimento Mensal | B6: =Rendimentos!G14 | C6: 1500 | D6: =IF(B6>=C6,"✓ Atingido","⚠ Abaixo") | E6: Fev | F6: =Rendimentos!G5 -> 830.4 | G6: =(F6-F5)/F5 -> 0.015283042
A7: Dividend Yield | B7: ='Painel de Controle'!B8 -> 0.039679088 | C7: 0.1 | D7: =IF(B7>=C7,"✓ Atingido","⚠ Abaixo") -> ⚠ Abaixo | E7: Mar | F7: =Rendimentos!G6 -> 844.6 | G7: =(F7-F6)/F6 -> 0.017100193
A8: Diversificação (nº FIIs) | B8: 12 | C8: 10 | D8: =IF(B8>=C8,"✓ Atingido","⚠ Abaixo") -> ✓ Atingido | E8: Abr | F8: =Rendimentos!G7 -> 858.7 | G8: =(F8-F7)/F7 -> 0.016694293
E9: Mai | F9: =Rendimentos!G8 -> 873.4 | G9: =(F9-F8)/F8 -> 0.017118901
E10: Jun | F10: =Rendimentos!G9 -> 888.6 | G10: =(F10-F9)/F9 -> 0.017403252
A11: CONCENTRAÇÃO POR CAPITALIZAÇÃO | E11: Jul | F11: =Rendimentos!G10 -> 904.1 | G11: =(F11-F10)/F10 -> 0.017443169
A12: Faixa de Investimento | B12: Quantidade | C12: % do Total | E12: Ago | F12: =Rendimentos!G11 -> 920.2 | G12: =(F12-F11)/F11 -> 0.017807765
A13: Até R$ 10.000 | B13: 3 | C13: 0.25 | E13: Set | F13: =Rendimentos!G12 -> 936.9 | G13: =(F13-F12)/F12 -> 0.018148229
A14: R$ 10.001 - R$ 15.000 | B14: 6 | C14: 0.5 | E14: Out | F14: =Rendimentos!G13 | G14: =(F14-F13)/F13
A15: Acima de R$ 15.000 | B15: 3 | C15: 0.25 | E15: Nov | F15: =Rendimentos!G14 | G15: =(F15-F14)/F14
E16: Dez | F16: =Rendimentos!G15 -> 989.8 | G16: =(F16-F15)/F15

Sheet Instruções
A1: 📖 GUIA DE USO DO SIMULADOR
A3: BEM-VINDO AO SIMULADOR DE INVESTIMENTOS EM FIIs!
A5: Esta ferramenta foi desenvolvida para auxiliar você na gestão e análise de seus investimentos
A6: em Fundos de Investimento Imobiliário (FIIs).
A8: 📊 ABAS DISPONÍVEIS:
A10: 1. PAINEL DE CONTROLE
A11: • Visão geral de todos os seus investimentos
A12: • Indicadores principais (Valor Investido, Rentabilidade, Dividend Yield)
A13: • Distribuição por setor (Residencial, Comercial, Industrial, Híbrido)
A15: 2. CARTEIRA
A16: • Registro detalhado de cada FII investido
A17: • Quantidade de cotas, preços médios e atuais
... A62: Versão: 1.0 | Data: 07/01/2026
